{
  "servant": {
    "no": "0086",
    "name": "謎のヒロインX",
    "clazz": "asasin",
    "rare": 5,
    "cost": 16,
    "tenchizin": "hoshi"
  },
  "card": {
    "arts": {
      "count": 2,
      "hit": 2
    },
    "quick": {
      "count": 2,
      "hit": 4
    },
    "buster": {
      "count": 1,
      "hit": 1
    }
  },
  "status": [
    {
      "level": "Lv90",
      "hp": 12696,
      "atk": 11761
    }
  ],
  "hidden": {
    "na": 0.81,
    "nd": 4,
    "dr": 38.5,
    "starcollection": 98,
    "staroccurrence": 25.6,
    "tag": [
      "混沌",
      "善",
      "女",
      "サーヴァント",
      "騎乗スキル",
      "人型",
      "竜",
      "アルトリア顔",
      "アーサー",
      "王",
      "ｴﾇﾏ特攻無効"
    ]
  },
  "classskill": [
    {
      "name": "コスモリアクターA",
      "effect": [
        {
          "type": "スター発生率アップ",
          "desc": "自身のスター発生率をアップ",
          "magnification": "10"
        }
      ]
    },
    {
      "name": "騎乗EX",
      "effect": [
        {
          "type": "Quickカード性能アップ",
          "desc": "自身のQuickカードの性能をアップ",
          "magnification": "12"
        }
      ]
    }
  ],
  "hogu": {
    "name": "無銘勝利剣(ひみつかりばー)",
    "card": "q",
    "effect": [
      {
        "type": "攻撃",
        "tern": 0,
        "count": 0,
        "target": "enemy-single",
        "beforeafter": "before",
        "lvoc": "lv",
        "desc": "敵単体に超強力な攻撃[Lv]",
        "v1": "1600",
        "v2": "2000",
        "v3": "2200",
        "v4": "2300",
        "v5": "2400"
      },
      {
        "type": "特攻",
        "tern": 0,
        "count": 0,
        "target": "enemy-single",
        "beforeafter": "after",
        "lvoc": "lv",
        "desc": "＆〔アルトリア顔〕特攻<OC:特攻威力UP>",
        "v1": "150",
        "v2": "162.5",
        "v3": "175",
        "v4": "187.5",
        "v5": "200"
      }
    ],
    "type": "single",
    "hit": 12
  },
  "skill1": {
    "name": "支援砲撃XEXEX",
    "ct": 9,
    "effects": [
      {
        "type": "防御力ダウン",
        "tern": "3",
        "count": 0,
        "target": "enemy-all",
        "desc": "敵全体の防御力をダウン[Lv](3T)",
        "v1": "10",
        "v2": "11",
        "v3": "12",
        "v4": "13",
        "v5": "14",
        "v6": "15",
        "v7": "16",
        "v8": "17",
        "v9": "18",
        "v10": "20"
      },
      {
        "type": "スタン付与",
        "tern": "1",
        "count": 0,
        "target": "enemy-all",
        "desc": "＋1ターン後に敵全体に中確率でスタン状態を付与する[Lv](1T)",
        "v1": "60",
        "v2": "62",
        "v3": "64",
        "v4": "66",
        "v5": "68",
        "v6": "70",
        "v7": "72",
        "v8": "74",
        "v9": "76",
        "v10": "80"
      }
    ]
  },
  "skill2": {
    "name": "セイバーの星C++",
    "ct": 7,
    "effects": [
      {
        "type": "無敵付与",
        "tern": "1",
        "count": 0,
        "target": "self",
        "desc": "自身に無敵状態を付与(1T)",
        "v1": "",
        "v2": "",
        "v3": "",
        "v4": "",
        "v5": "",
        "v6": "",
        "v7": "",
        "v8": "",
        "v9": "",
        "v10": ""
      },
      {
        "type": "スター獲得",
        "tern": 0,
        "count": 0,
        "target": "self",
        "desc": "＋スターを大量獲得[Lv]",
        "v1": "10",
        "v2": "11",
        "v3": "12",
        "v4": "13",
        "v5": "14",
        "v6": "15",
        "v7": "16",
        "v8": "17",
        "v9": "18",
        "v10": "20"
      }
    ]
  },
  "skill3": {
    "name": "銀河流星剣C",
    "ct": 8,
    "effects": [
      {
        "type": "スター発生率アップ",
        "tern": "3",
        "count": 0,
        "target": "self",
        "desc": "自身の〔セイバー〕に対する攻撃時のスター発生率を超アップ[Lv](3T)",
        "v1": "50",
        "v2": "55",
        "v3": "60",
        "v4": "65",
        "v5": "70",
        "v6": "75",
        "v7": "80",
        "v8": "85",
        "v9": "90",
        "v10": "100"
      },
      {
        "type": "特攻付与",
        "tern": "3",
        "count": 0,
        "target": "self",
        "desc": "＆〔セイバー〕特攻状態を付与[Lv](3T)",
        "v1": "30",
        "v2": "32",
        "v3": "34",
        "v4": "36",
        "v5": "38",
        "v6": "40",
        "v7": "42",
        "v8": "44",
        "v9": "46",
        "v10": "50"
      }
    ]
  }
}