{
  "servant": {
    "no": "0139",
    "name": "クレオパトラ",
    "clazz": "asasin",
    "rare": 5,
    "cost": 16,
    "tenchizin": "hito"
  },
  "card": {
    "arts": {
      "count": 1,
      "hit": 2
    },
    "quick": {
      "count": 2,
      "hit": 4
    },
    "buster": {
      "count": 2,
      "hit": 3
    }
  },
  "status": [
    {
      "level": "Lv90",
      "hp": 13402,
      "atk": 11088
    }
  ],
  "hidden": {
    "na": 1.06,
    "nd": 4,
    "dr": 49.5,
    "starcollection": 98,
    "staroccurrence": 25.5,
    "tag": [
      "秩序",
      "中庸",
      "女",
      "サーヴァント",
      "人型",
      "神性",
      "王"
    ]
  },
  "classskill": [
    {
      "name": "気配遮断B",
      "effect": [
        {
          "type": "スター発生率アップ",
          "desc": "自身のスター発生率をアップ",
          "magnification": "8"
        }
      ]
    },
    {
      "name": "神性D",
      "effect": [
        {
          "type": "与ダメージプラス付与",
          "desc": "自身に与ダメージプラス状態を付与",
          "magnification": "125"
        }
      ]
    }
  ],
  "hogu": {
    "name": "暁の時を終える蛇よ、此処に(ウラエウス・アストラペ)",
    "card": "b",
    "effect": [
      {
        "type": "Busterカード性能アップ",
        "tern": "1",
        "count": 0,
        "target": "self",
        "beforeafter": "before",
        "lvoc": "oc",
        "desc": "自身のBusterカード性能をアップ(1T)<OC:効果UP>",
        "v1": "30",
        "v2": "40",
        "v3": "50",
        "v4": "60",
        "v5": "70"
      },
      {
        "type": "攻撃",
        "tern": 0,
        "count": 0,
        "target": "enemy-all",
        "beforeafter": "before",
        "lvoc": "lv",
        "desc": "＋敵全体に強力な攻撃[Lv]",
        "v1": "400",
        "v2": "500",
        "v3": "550",
        "v4": "575",
        "v5": "600"
      },
      {
        "type": "強化無効付与",
        "tern": "3",
        "count": "1",
        "target": "enemy-all",
        "beforeafter": "after",
        "lvoc": "lv",
        "desc": "＆強化無効状態を付与(1回・3T)",
        "v1": "",
        "v2": "",
        "v3": "",
        "v4": "",
        "v5": ""
      },
      {
        "type": "HP減少",
        "tern": 0,
        "count": 0,
        "target": "self",
        "beforeafter": "after",
        "lvoc": "lv",
        "desc": "＋自身のHPを1000減らす【デメリット】",
        "v1": "1000",
        "v2": "1000",
        "v3": "1000",
        "v4": "1000",
        "v5": "1000"
      }
    ],
    "type": "all",
    "hit": 5
  },
  "skill1": {
    "name": "皇帝特権A",
    "ct": 7,
    "effects": [
      {
        "type": "攻撃力アップ",
        "tern": "3",
        "count": 0,
        "target": "self",
        "desc": "自身の攻撃力アップ(3T) [Lv] 確率60％",
        "v1": "20",
        "v2": "22",
        "v3": "24",
        "v4": "26",
        "v5": "28",
        "v6": "30",
        "v7": "32",
        "v8": "34",
        "v9": "36",
        "v10": "40"
      },
      {
        "type": "防御力アップ",
        "tern": "3",
        "count": 0,
        "target": "self",
        "desc": "＆防御力をアップ(3T) [Lv] 確率60％",
        "v1": "20",
        "v2": "22",
        "v3": "24",
        "v4": "26",
        "v5": "28",
        "v6": "30",
        "v7": "32",
        "v8": "34",
        "v9": "36",
        "v10": "40"
      },
      {
        "type": "HP回復",
        "tern": 0,
        "count": 0,
        "target": "self",
        "desc": "＆HP回復 [Lv]",
        "v1": "1000",
        "v2": "1200",
        "v3": "1400",
        "v4": "1600",
        "v5": "1800",
        "v6": "2000",
        "v7": "2200",
        "v8": "2400",
        "v9": "2600",
        "v10": "3000"
      }
    ]
  },
  "skill2": {
    "name": "黄金律（富＆体）B",
    "ct": 8,
    "effects": [
      {
        "type": "NP獲得量アップ",
        "tern": "3",
        "count": 0,
        "target": "self",
        "desc": "自身のNP獲得量をアップ[Lv](3T)",
        "v1": "20",
        "v2": "22",
        "v3": "24",
        "v4": "26",
        "v5": "28",
        "v6": "30",
        "v7": "32",
        "v8": "34",
        "v9": "36",
        "v10": "40"
      },
      {
        "type": "NP獲得状態付与",
        "tern": "3",
        "count": 0,
        "target": "self",
        "desc": "＆毎ターンNP獲得状態を付与(3T)",
        "v1": "10",
        "v2": "10",
        "v3": "10",
        "v4": "10",
        "v5": "10",
        "v6": "10",
        "v7": "10",
        "v8": "10",
        "v9": "10",
        "v10": "10"
      },
      {
        "type": "HP回復",
        "tern": "3",
        "count": 0,
        "target": "self",
        "desc": "＆毎ターンHP回復状態を付与[Lv](3T)",
        "v1": "500",
        "v2": "550",
        "v3": "600",
        "v4": "650",
        "v5": "700",
        "v6": "750",
        "v7": "800",
        "v8": "850",
        "v9": "900",
        "v10": "1000"
      }
    ]
  },
  "skill3": {
    "name": "女神の加護C",
    "ct": 8,
    "effects": [
      {
        "type": "無敵付与",
        "tern": "1",
        "count": 0,
        "target": "self",
        "desc": "自身に無敵状態を付与(1T)",
        "v1": "",
        "v2": "",
        "v3": "",
        "v4": "",
        "v5": "",
        "v6": "",
        "v7": "",
        "v8": "",
        "v9": "",
        "v10": ""
      },
      {
        "type": "弱体解除",
        "tern": 0,
        "count": 0,
        "target": "self",
        "desc": "＆弱体状態を解除",
        "v1": "",
        "v2": "",
        "v3": "",
        "v4": "",
        "v5": "",
        "v6": "",
        "v7": "",
        "v8": "",
        "v9": "",
        "v10": ""
      },
      {
        "type": "スター獲得",
        "tern": 0,
        "count": 0,
        "target": "self",
        "desc": "＆スター獲得[Lv]",
        "v1": "10",
        "v2": "11",
        "v3": "12",
        "v4": "13",
        "v5": "14",
        "v6": "15",
        "v7": "16",
        "v8": "17",
        "v9": "18",
        "v10": "20"
      }
    ]
  }
}