{
	"servant": {
		"name": "諸葛孔明〔エルメロイⅡ世〕",
		"clazz": "caster",
		"rare": 5,
		"cost": 16,
		"tenchizin": "hito",
		"no" : "0037"
	},
	"card": {
		"arts": {
			"count": 3,
			"hit": 1
		},
		"quick": {
			"count": 1,
			"hit": 2
		},
		"buster": {
			"count": 1,
			"hit": 1
		}
	},
	"status": [
		{
			"level": "90",
			"hp": 14259,
			"atk": 10598
		},
		{
			"level": "100",
			"hp": 15621,
			"atk": 11601
		}
	],
	"hidden": {
		"na": 1.64,
		"staroccurrence": 10.8,
		"starcollection": 50,
		"dr": 34.5,
		"nd": 3,
		"tag": [
			"中立",
			"善",
			"男",
			"サーヴァント",
			"人型",
			"愛する者"
		]
	},
	"classskill": [
		{
			"name": "陣地作成A",
			"effect": [
				{
					"type": "Artsカード性能アップ",
					"magnification": "10",
					"desc": "自身のArtsカードの性能をアップ"
				}
			]
		},
		{
			"name": "道具作成B",
			"effect": [
				{
					"type": "弱体耐性アップ",
					"magnification": "8",
					"desc": "自身の弱体付与成功率をアップ"
				}
			]
		}
	],
	"skill1": {
		"name": "鑑識眼 A",
		"ct": 7,
		"effect": [
			{
				"type": "クリティカル威力アップ",
				"tern": 3,
				"count": 0,
				"target": "other-single",
				"desc": "味方単体のクリティカル威力をアップ[Lv](3T)",
				"v1": "20",
				"v2": "23",
				"v3": "26",
				"v4": "29",
				"v5": "32",
				"v6": "35",
				"v7": "38",
				"v8": "41",
				"v9": "44",
				"v10": "50"
			},
			{
				"type": "NP増加",
				"tern": 0,
				"count": 0,
				"target": "other-single",
				"desc": "NPを増やす",
				"v1": "30",
				"v2": "30",
				"v3": "30",
				"v4": "30",
				"v5": "30",
				"v6": "30",
				"v7": "30",
				"v8": "30",
				"v9": "30",
				"v10": "30"
			}
		]
	},
	"skill2": {
		"name": "軍師の忠言 A+",
		"ct": 8,
		"effect": [
			{
				"type": "防御力アップ",
				"tern": 3,
				"count": 0,
				"target": "self-other",
				"desc": "味方全体の防御力をアップ[Lv](3T)",
				"v1": "20",
				"v2": "21",
				"v3": "22",
				"v4": "23",
				"v5": "24",
				"v6": "25",
				"v7": "26",
				"v8": "27",
				"v9": "28",
				"v10": "30"
			},
			{
				"type": "ダメージカット付与",
				"tern": 3,
				"count": 0,
				"target": "self-other",
				"desc": "被ダメージカット状態を付与[Lv](3T)",
				"v1": "200",
				"v2": "230",
				"v3": "260",
				"v4": "290",
				"v5": "320",
				"v6": "350",
				"v7": "380",
				"v8": "410",
				"v9": "440",
				"v10": "500"
			},
			{
				"type": "NP増加",
				"tern": 0,
				"count": 0,
				"target": "self-other",
				"desc": "NPを少し増やす",
				"v1": "10",
				"v2": "10",
				"v3": "10",
				"v4": "10",
				"v5": "10",
				"v6": "10",
				"v7": "10",
				"v8": "10",
				"v9": "10",
				"v10": "10"
			}
		]
	},
	"skill3": {
		"name": "軍師の指揮 A+",
		"ct": 8,
		"effect": [
			{
				"type": "攻撃力アップ",
				"tern": 3,
				"count": 0,
				"target": "self-other",
				"desc": "味方全体の攻撃力をアップ[Lv](3T)",
				"v1": "20",
				"v2": "21",
				"v3": "22",
				"v4": "23",
				"v5": "24",
				"v6": "25",
				"v7": "26",
				"v8": "27",
				"v9": "28",
				"v10": "30"
			},
			{
				"type": "与ダメージプラス付与",
				"tern": 3,
				"count": 0,
				"target": "self-other",
				"desc": "与ダメージプラス状態を付与[Lv](3T)",
				"v1": "200",
				"v2": "230",
				"v3": "260",
				"v4": "290",
				"v5": "320",
				"v6": "350",
				"v7": "380",
				"v8": "410",
				"v9": "440",
				"v10": "500"
			},
			{
				"type": "NP増加",
				"tern": 0,
				"count": 0,
				"target": "self-other",
				"desc": "NPを少し増やす",
				"v1": "10",
				"v2": "10",
				"v3": "10",
				"v4": "10",
				"v5": "10",
				"v6": "10",
				"v7": "10",
				"v8": "10",
				"v9": "10",
				"v10": "10"
			}
		]
	},
	"hogu": {
		"name": "石兵八陣\t",
		"type": "support",
		"card": "a",
		"hit": 0,
		"effect": [
			{
				"type": "チャージ減",
				"tern": 0,
				"count": 0,
				"target": "enemy-all",
				"beforeafter": "before",
				"lvoc": "lv",
				"desc": "敵全体のチャージを減らす",
				"v1": "0",
				"v2": "0",
				"v3": "0",
				"v4": "0",
				"v5": "0"
			},
			{
				"type": "スタン付与",
				"tern": 0,
				"count": 0,
				"target": "enemy-all",
				"beforeafter": "before",
				"lvoc": "oc",
				"desc": "中確率でスタン状態を付与(1T)<OC:確率UP>",
				"v1": "50",
				"v2": "57.5",
				"v3": "65",
				"v4": "72.5",
				"v5": "80"
			},
			{
				"type": "呪い付与",
				"tern": 6,
				"count": 0,
				"target": "enemy-all",
				"beforeafter": "before",
				"lvoc": "lv",
				"desc": "呪い状態を付与",
				"v1": "1000",
				"v2": "1000",
				"v3": "1000",
				"v4": "1000",
				"v5": "1000"
			},
			{
				"type": "防御力ダウン",
				"tern": 3,
				"count": 0,
				"target": "enemy-all",
				"beforeafter": "before",
				"lvoc": "lv",
				"desc": "防御力を大ダウン",
				"v1": "30",
				"v2": "40",
				"v3": "45",
				"v4": "47.5",
				"v5": "50"
			}
		]
	}
}